paranoid_deobfuscator/__init__.py
paranoid_deobfuscator/__main__.py
paranoid_deobfuscator/commands/__init__.py
paranoid_deobfuscator/commands/deobfuscate.py
paranoid_deobfuscator/commands/helpers.py
paranoid_deobfuscator/constants.py
paranoid_deobfuscator/encoding.py
paranoid_deobfuscator/paranoid/DeobfuscatorHelper.py
paranoid_deobfuscator/paranoid/RandomHelper.py
paranoid_deobfuscator/paranoid/__init__.py
paranoid_deobfuscator/paranoid/utils.py
paranoid_deobfuscator/smali/__init__.py
paranoid_deobfuscator/smali/instructions.py
paranoid_deobfuscator/smali/register.py
paranoid_deobfuscator-3.0.2.dist-info/LICENSE
paranoid_deobfuscator-3.0.2.dist-info/METADATA
paranoid_deobfuscator-3.0.2.dist-info/WHEEL
paranoid_deobfuscator-3.0.2.dist-info/entry_points.txt
paranoid_deobfuscator-3.0.2.dist-info/RECORD
