Metadata-Version: 2.1
Name: paranoid-deobfuscator
Version: 3.0.2
Summary: Deobfuscate "paranoid" obfuscated apps
Home-page: https://github.com/giacomoferretti/paranoid-deobfuscator
License: Apache-2.0
Author: Giacomo Ferretti
Author-email: giacomo.ferretti.00@gmail.com
Requires-Python: >=3.10,<4.0
Classifier: Intended Audience :: Developers
Classifier: Intended Audience :: Information Technology
Classifier: Intended Audience :: Science/Research
Classifier: License :: OSI Approved :: Apache Software License
Classifier: Programming Language :: Python :: 3
Classifier: Programming Language :: Python :: 3.10
Classifier: Programming Language :: Python :: 3.11
Classifier: Programming Language :: Python :: 3.12
Classifier: Programming Language :: Python :: 3.13
Classifier: Topic :: Security
Classifier: Topic :: Software Development :: Libraries :: Python Modules
Requires-Dist: click (>=8.1.7,<9.0.0)
Requires-Dist: numpy (>=2.1.3,<3.0.0)
Project-URL: Bug Tracker, https://github.com/giacomoferretti/paranoid-deobfuscator/issues
Project-URL: Repository, https://github.com/giacomoferretti/paranoid-deobfuscator
